ansys/hps/data_transfer/client/__init__.py
ansys/hps/data_transfer/client/__version__.py
ansys/hps/data_transfer/client/authenticate.py
ansys/hps/data_transfer/client/binary.py
ansys/hps/data_transfer/client/client.py
ansys/hps/data_transfer/client/exceptions.py
ansys/hps/data_transfer/client/token.py
ansys/hps/data_transfer/client/api/__init__.py
ansys/hps/data_transfer/client/api/api.py
ansys/hps/data_transfer/client/api/async_api.py
ansys/hps/data_transfer/client/api/retry.py
ansys/hps/data_transfer/client/models/__init__.py
ansys/hps/data_transfer/client/models/common.py
ansys/hps/data_transfer/client/models/core.py
ansys/hps/data_transfer/client/models/metadata.py
ansys/hps/data_transfer/client/models/msg.py
ansys/hps/data_transfer/client/models/ops.py
ansys/hps/data_transfer/client/models/permissions.py
ansys/hps/data_transfer/client/models/rest.py
ansys/hps/data_transfer/client/models/storage.py
ansys/hps/data_transfer/client/utils/__init__.py
ansys/hps/data_transfer/client/utils/jitter.py
ansys/hps/data_transfer/client/utils/otel_config.py
ansys_hps_data_transfer_client-0.3.1.dist-info/LICENSE
ansys_hps_data_transfer_client-0.3.1.dist-info/WHEEL
ansys_hps_data_transfer_client-0.3.1.dist-info/METADATA
ansys_hps_data_transfer_client-0.3.1.dist-info/RECORD
