Metadata-Version: 2.3
Name: ansys-hps-data-transfer-client
Version: 0.3.1
Summary: Python client library for hps data transfer service
Author-email: "ANSYS, Inc." <pyansys.core@ansys.com>
Maintainer-email: "ANSYS, Inc." <pyansys.core@ansys.com>
Requires-Python: >=3.10,<4.0
Classifier: Development Status :: 4 - Beta
Classifier: Programming Language :: Python :: 3.10
Classifier: Programming Language :: Python :: 3.11
Classifier: Programming Language :: Python :: 3.12
Classifier: License :: OSI Approved :: MIT License
Classifier: Operating System :: OS Independent
Requires-Dist: pydantic>=2.7.1
Requires-Dist: httpx>=0.27.0
Requires-Dist: backoff>=2.2.1
Requires-Dist: humanfriendly>=10.0
Requires-Dist: requests>=2.21.0
Requires-Dist: portend>=3.2.0
Requires-Dist: filelock>=3.14.0
Requires-Dist: psutil>=5.9.1
Requires-Dist: asyncio-atexit>=1.0.0
Requires-Dist: build==1.2.2.post1 ; extra == "build"
Requires-Dist: twine==6.1.0 ; extra == "build"
Requires-Dist: wheel ; extra == "build"
Requires-Dist: datamodel-code-generator==0.32.0 ; extra == "build"
Requires-Dist: pre-commit==4.2.0 ; extra == "build"
Requires-Dist: importlib_metadata>=7.0 ; extra == "build"
Requires-Dist: ansys-sphinx-theme==1.6.1 ; extra == "doc"
Requires-Dist: autodoc_pydantic==2.2.0 ; extra == "doc"
Requires-Dist: jupyter_sphinx==0.5.3 ; extra == "doc"
Requires-Dist: nbsphinx==0.9.7 ; extra == "doc"
Requires-Dist: numpydoc==1.8.0 ; extra == "doc"
Requires-Dist: Sphinx==8.1.3 ; extra == "doc"
Requires-Dist: sphinx-autoapi==3.6.1 ; extra == "doc"
Requires-Dist: sphinx-autodoc-typehints==3.0.1 ; extra == "doc"
Requires-Dist: sphinxcontrib-globalsubs==0.1.2 ; extra == "doc"
Requires-Dist: sphinxcontrib-httpdomain==1.8.1 ; extra == "doc"
Requires-Dist: sphinx-copybutton==0.5.2 ; extra == "doc"
Requires-Dist: sphinx_design==0.6.1 ; extra == "doc"
Requires-Dist: sphinx-jinja==2.0.2 ; extra == "doc"
Requires-Dist: sphinxnotes-strike==1.2.1 ; extra == "doc"
Requires-Dist: sphinx-tabs==3.4.7 ; extra == "doc"
Requires-Dist: sphinx-gallery==0.19.0 ; extra == "doc"
Requires-Dist: pytest==8.4.1 ; extra == "tests"
Requires-Dist: pytest-cov==6.2.1 ; extra == "tests"
Requires-Dist: pytest-timeout==2.4.0 ; extra == "tests"
Requires-Dist: pytest-mock-resources[redis]==2.12.2 ; extra == "tests"
Requires-Dist: pytest-rerunfailures==15.1 ; extra == "tests"
Requires-Dist: pytest-asyncio==1.1.0 ; extra == "tests"
Requires-Dist: python-keycloak==5.7.0 ; extra == "tests"
Requires-Dist: python-slugify>=8.0.4 ; extra == "tests"
Requires-Dist: tox==4.28.4 ; extra == "tests"
Project-URL: Documentation, https://data-transfer.hps.docs.pyansys.com
Project-URL: Homepage, https://github.com/ansys/pyhps-data-transfer/
Project-URL: Source, https://github.com/ansys/pyhps-data-transfer/
Project-URL: Tracker, https://github.com/ansys/pyhps-data-transfer/issues
Provides-Extra: build
Provides-Extra: doc
Provides-Extra: tests
